idoit_scaleup/__init__.py
idoit_scaleup/api_log.py
idoit_scaleup/base.py
idoit_scaleup/cat_access.py
idoit_scaleup/cat_application.py
idoit_scaleup/cat_connector.py
idoit_scaleup/cat_cpu.py
idoit_scaleup/cat_ip.py
idoit_scaleup/cat_location.py
idoit_scaleup/cat_memory.py
idoit_scaleup/cat_network.py
idoit_scaleup/cat_network_log_port.py
idoit_scaleup/cat_networkport.py
idoit_scaleup/cat_power_consumer.py
idoit_scaleup/cat_racktables.py
idoit_scaleup/cat_storage_device.py
idoit_scaleup/cat_vlan.py
idoit_scaleup/category.py
idoit_scaleup/conditional_read.py
idoit_scaleup/consts.py
idoit_scaleup/dialog.py
idoit_scaleup/object.py
idoit_scaleup/search.py
idoit_scaleup-0.0.18.dist-info/METADATA
idoit_scaleup-0.0.18.dist-info/WHEEL
idoit_scaleup-0.0.18.dist-info/licenses/LICENSE
idoit_scaleup-0.0.18.dist-info/RECORD
